piplibaryscrape/__init__.py
piplibaryscrape-1.0.0.dist-info/METADATA
piplibaryscrape-1.0.0.dist-info/WHEEL
piplibaryscrape-1.0.0.dist-info/top_level.txt
piplibaryscrape-1.0.0.dist-info/RECORD
